tarmac/metadata.py
tarmac/cli.py
tarmac/__init__.py
tarmac/__main__.py
tarmac/runner.py
tarmac/operations.py
tarmac/__version__.py
tarmac-0.1.9.dist-info/WHEEL
tarmac-0.1.9.dist-info/entry_points.txt
tarmac-0.1.9.dist-info/METADATA
tarmac-0.1.9.dist-info/RECORD
