Metadata-Version: 2.3
Name: tarmac
Version: 0.1.9
Summary: Reliable deployments, repeatable workflows
License: The MIT License (MIT)
Requires-Dist: dotmap>=1.3.30
Requires-Dist: pydantic>=2.10.6
Requires-Dist: pyyaml>=6.0.2
Requires-Dist: uv>=0.6.10
Requires-Python: >=3.12
